demo_pk/__init__.py
demo_pk/demo.py
zy_demo-1.0.0.dist-info/LICENSE
zy_demo-1.0.0.dist-info/METADATA
zy_demo-1.0.0.dist-info/WHEEL
zy_demo-1.0.0.dist-info/top_level.txt
zy_demo-1.0.0.dist-info/RECORD
