Metadata-Version: 2.1
Name: zy_demo
Version: 1.0.0
Summary: simple demo package
Author: zhengyu
Author-email: 543278005@qq.com
Classifier: Programming Language :: Python :: 3
Classifier: License :: OSI Approved :: MIT License
Classifier: Operating System :: OS Independent
Requires-Python: >=3
License-File: LICENSE
Requires-Dist: numpy
Requires-Dist: opencv-python
